iceqube/__init__.py
iceqube/classes.py
iceqube/compat.py
iceqube/exceptions.py
iceqube/queue.py
iceqube/storage.py
iceqube/utils.py
iceqube/worker.py
iceqube-0.4.dist-info/LICENSE
iceqube-0.4.dist-info/METADATA
iceqube-0.4.dist-info/WHEEL
iceqube-0.4.dist-info/top_level.txt
iceqube-0.4.dist-info/zip-safe
iceqube-0.4.dist-info/RECORD
