Metadata-Version: 2.1
Name: iceqube
Version: 0.4
Summary: UNKNOWN
Home-page: https://github.com/learningequality/iceqube
Author: Learning Equality
Author-email: aron@learningequality.org
License: MIT
Keywords: queue,async
Platform: UNKNOWN
Classifier: Development Status :: 2 - Pre-Alpha
Classifier: Intended Audience :: Developers
Classifier: License :: OSI Approved :: MIT License
Classifier: Natural Language :: English
Classifier: Programming Language :: Python :: 2
Classifier: Programming Language :: Python :: 2.7
Classifier: Programming Language :: Python :: 3
Classifier: Programming Language :: Python :: 3.4
Classifier: Programming Language :: Python :: 3.5
Classifier: Programming Language :: Python :: 3.6
Classifier: Programming Language :: Python :: 3.7
Requires-Dist: SQLAlchemy (>=1.1.10)
Requires-Dist: futures (>=3.1.1)
